pyQuadriFlow/__init__.py
pyQuadriFlow/pyQuadriFlow.py
pyQuadriFlow/clib/__init__.py
pyQuadriFlow/clib/ctypes_QuadriFlow.dll
pyQuadriFlow/clib/ctypes_QuadriFlow.so
pyQuadriFlow/clib/load_library.py
pyquadriflow-0.0.4.dist-info/METADATA
pyquadriflow-0.0.4.dist-info/WHEEL
pyquadriflow-0.0.4.dist-info/licenses/LICENSE
pyquadriflow-0.0.4.dist-info/RECORD
