Metadata-Version: 2.3
Name: pyQuadriFlow
Version: 0.0.4
Summary: Python QuadriFlow wrapper
Project-URL: Homepage, https://github.com/satabol/pyQuadriFlow
Project-URL: Issues, https://github.com/satabol/pyQuadriFlow/issues
Author-email: Satabol <satabol@yandex.ru>
License-File: LICENSE
Keywords: quad,quadrangulation,quadriflow,remeshing
Classifier: Development Status :: 2 - Pre-Alpha
Classifier: Intended Audience :: Developers
Classifier: Operating System :: Microsoft :: Windows
Classifier: Operating System :: Unix
Classifier: Programming Language :: Python :: 3
Requires-Python: >=3.8
